Metadata-Version: 2.1
Name: scHiCTools
Version: 0.0.3
Summary: A user-friendly package for processing single cell HiC data
Home-page: https://github.com/liu-bioinfo-lab/scHiCTool
Author: Fan Feng
Author-email: fanfeng@umich.edu
License: UNKNOWN
Platform: UNKNOWN
Classifier: Programming Language :: Python :: 3
Classifier: License :: OSI Approved :: MIT License
Classifier: Operating System :: OS Independent
Provides-Extra: interactive_scatter
